odoo/addons/resource_multi_week_calendar/README.rst
odoo/addons/resource_multi_week_calendar/__init__.py
odoo/addons/resource_multi_week_calendar/__manifest__.py
odoo/addons/resource_multi_week_calendar/i18n/it.po
odoo/addons/resource_multi_week_calendar/i18n/resource_multi_week_calendar.pot
odoo/addons/resource_multi_week_calendar/models/__init__.py
odoo/addons/resource_multi_week_calendar/models/resource_calendar.py
odoo/addons/resource_multi_week_calendar/readme/CONTRIBUTORS.rst
odoo/addons/resource_multi_week_calendar/readme/DESCRIPTION.rst
odoo/addons/resource_multi_week_calendar/readme/ROADMAP.rst
odoo/addons/resource_multi_week_calendar/static/description/icon.png
odoo/addons/resource_multi_week_calendar/static/description/index.html
odoo/addons/resource_multi_week_calendar/tests/__init__.py
odoo/addons/resource_multi_week_calendar/tests/test_calendar.py
odoo/addons/resource_multi_week_calendar/views/resource_calendar_views.xml
odoo_addon_resource_multi_week_calendar-16.0.1.0.0.17.dist-info/METADATA
odoo_addon_resource_multi_week_calendar-16.0.1.0.0.17.dist-info/WHEEL
odoo_addon_resource_multi_week_calendar-16.0.1.0.0.17.dist-info/top_level.txt
odoo_addon_resource_multi_week_calendar-16.0.1.0.0.17.dist-info/RECORD
